jsobject.py
jsobject-0.0.1_dev.data/scripts/jsobject.py
jsobject-0.0.1_dev.dist-info/DESCRIPTION.rst
jsobject-0.0.1_dev.dist-info/METADATA
jsobject-0.0.1_dev.dist-info/metadata.json
jsobject-0.0.1_dev.dist-info/RECORD
jsobject-0.0.1_dev.dist-info/top_level.txt
jsobject-0.0.1_dev.dist-info/WHEEL
