Metadata-Version: 2.0
Name: jsobject
Version: 0.0.1-dev
Summary: Jsobject is simple implementation JavaScript-Style Objects in Python.
Home-page: http://mavier.github.io/jsobject
Author: Marcin Wierzbanowski
Author-email: marcin@wierzbanowski.com
License: MIT
Keywords: jsobject,json,chain,javascript,object
Platform: any
Classifier: Development Status :: 1 - Planning
Classifier: Intended Audience :: Developers
Classifier: License :: OSI Approved :: MIT License
Classifier: Intended Audience :: Developers
Classifier: Operating System :: OS Independent
Classifier: Topic :: Software Development
Classifier: Topic :: Software Development :: Libraries
Classifier: Topic :: Utilities
Classifier: Programming Language :: Python
Classifier: Programming Language :: Python :: 2.5
Classifier: Programming Language :: Python :: 2.6
Classifier: Programming Language :: Python :: 2.7
Classifier: Programming Language :: Python :: 3
Classifier: Programming Language :: Python :: 3.2
Classifier: Programming Language :: Python :: 3.3
